sedaro/__init__.py
sedaro/data_utils.py
sedaro/exceptions.py
sedaro/modsim.py
sedaro/plain_request.py
sedaro/sedaro_api_client.py
sedaro/settings.py
sedaro/utils.py
sedaro/branches/__init__.py
sedaro/branches/agent_template_branch.py
sedaro/branches/branch.py
sedaro/branches/common.py
sedaro/branches/blocks/__init__.py
sedaro/branches/blocks/block.py
sedaro/branches/blocks/block_type.py
sedaro/branches/scenario_branch/__init__.py
sedaro/branches/scenario_branch/download.py
sedaro/branches/scenario_branch/scenario_branch.py
sedaro/branches/scenario_branch/sim_client.py
sedaro/branches/scenario_branch/study_client.py
sedaro/branches/scenario_branch/utils.py
sedaro/grpc_client/__init__.py
sedaro/grpc_client/cosim_client.py
sedaro/grpc_client/cosim_pb2.py
sedaro/grpc_client/cosim_pb2_grpc.py
sedaro/models/BaseModel.py
sedaro/models/BaseModelManager.py
sedaro/models/branch/__init__.py
sedaro/models/branch/main.py
sedaro/models/project/__init__.py
sedaro/models/project/main.py
sedaro/models/repository/__init__.py
sedaro/models/repository/main.py
sedaro/models/workspace/__init__.py
sedaro/models/workspace/main.py
sedaro/results/__init__.py
sedaro/results/agent.py
sedaro/results/block.py
sedaro/results/series.py
sedaro/results/simulation_result.py
sedaro/results/study.py
sedaro/results/utils.py
sedaro-4.19.13.dist-info/licenses/LICENSE
sedaro_base_client/__init__.py
sedaro_base_client/api_client.py
sedaro_base_client/configuration.py
sedaro_base_client/exceptions.py
sedaro_base_client/rest.py
sedaro_base_client/schemas.py
sedaro_base_client/apis/__init__.py
sedaro_base_client/apis/path_to_api.py
sedaro_base_client/apis/tag_to_api.py
sedaro_base_client/apis/paths/__init__.py
sedaro_base_client/apis/paths/data_id.py
sedaro_base_client/apis/paths/models_branches_branch_id.py
sedaro_base_client/apis/paths/models_branches_branch_id_changes_.py
sedaro_base_client/apis/paths/models_branches_branch_id_commits_.py
sedaro_base_client/apis/paths/models_branches_branch_id_committed_.py
sedaro-4.19.13.dist-info/METADATA
sedaro-4.19.13.dist-info/WHEEL
sedaro-4.19.13.dist-info/top_level.txt
sedaro-4.19.13.dist-info/RECORD
