Metadata-Version: 2.4
Name: sedaro
Version: 4.19.13
Summary: A python client to interact with the Sedaro API.
Author-email: Sedaro <support@sedarotech.com>
Project-URL: Homepage, https://github.com/sedaro/sedaro-python
Project-URL: Bug Tracker, https://github.com/sedaro/sedaro-python/issues
Classifier: Programming Language :: Python :: 3.9
Classifier: License :: OSI Approved :: GNU General Public License v3 (GPLv3)
Classifier: Operating System :: OS Independent
Classifier: Topic :: Software Development
Requires-Python: >=3.9
License-File: LICENSE
Requires-Dist: certifi>=14.5.14
Requires-Dist: dask[dataframe]~=2024.5
Requires-Dist: flatdict~=4.0.1
Requires-Dist: frozendict~=2.3.4
Requires-Dist: msgpack~=1.1.0
Requires-Dist: python-dateutil~=2.7
Requires-Dist: setuptools>=21.0.0
Requires-Dist: tqdm~=4.66.1
Requires-Dist: typing_extensions<4.14.0,>=4.3.0
Requires-Dist: urllib3~=1.26.7
Requires-Dist: uuid6~=2023.5.2
Requires-Dist: pydash>=5.1.1
Requires-Dist: scipy>=1.10.1
Requires-Dist: numpy
Requires-Dist: orjson
Requires-Dist: pyarrow
Requires-Dist: requests
Requires-Dist: spiceypy
Requires-Dist: grpcio
Requires-Dist: grpcio-tools
Requires-Dist: protobuf
Requires-Dist: openpyxl
Requires-Dist: pytz==2024.1
Dynamic: license-file
